ez_automl_lite/README.md
ez_automl_lite/__init__.py
ez_automl_lite/_version.py
ez_automl_lite/core/__init__.py
ez_automl_lite/core/anomaly.py
ez_automl_lite/core/cluster.py
ez_automl_lite/core/exporter.py
ez_automl_lite/core/preprocessor.py
ez_automl_lite/core/trainer.py
ez_automl_lite/reports/__init__.py
ez_automl_lite/reports/anomaly_report.py
ez_automl_lite/reports/cluster_report.py
ez_automl_lite/reports/eda.py
ez_automl_lite/reports/training.py
ez_automl_lite/utils/__init__.py
ez_automl_lite/utils/detection.py
ez_automl_lite-0.1.0b1.dist-info/licenses/LICENSE
ez_automl_lite-0.1.0b1.dist-info/METADATA
ez_automl_lite-0.1.0b1.dist-info/WHEEL
ez_automl_lite-0.1.0b1.dist-info/top_level.txt
ez_automl_lite-0.1.0b1.dist-info/RECORD
