Metadata-Version: 2.4
Name: ez-automl-lite
Version: 0.1.0b1
Summary: A lightweight AutoML library optimized for simple APIs and ONNX export.
Author-email: Cristopher Coronado <cgcoronadom@gmail.com>
License: MIT
Project-URL: Homepage, https://github.com/cristofima/auto-ml-lite
Project-URL: Issues, https://github.com/cristofima/auto-ml-lite/issues
Project-URL: Repository, https://github.com/cristofima/auto-ml-lite
Classifier: Programming Language :: Python :: 3
Classifier: License :: OSI Approved :: MIT License
Classifier: Operating System :: OS Independent
Requires-Python: >=3.11
License-File: LICENSE
Requires-Dist: flaml[automl]>=2.3.6
Requires-Dist: pandas>=2.2.0
Requires-Dist: numpy>=1.26.0
Requires-Dist: scikit-learn>=1.4.0
Requires-Dist: feature-engine>=1.8.1
Requires-Dist: joblib>=1.3.2
Requires-Dist: lightgbm>=4.3.0
Provides-Extra: onnx
Requires-Dist: skl2onnx>=1.17.0; extra == "onnx"
Requires-Dist: onnx>=1.16.0; extra == "onnx"
Requires-Dist: onnxruntime>=1.18.0; extra == "onnx"
Requires-Dist: onnxmltools>=1.12.0; extra == "onnx"
Provides-Extra: reports
Requires-Dist: sweetviz>=2.3.1; extra == "reports"
Provides-Extra: all
Requires-Dist: ez-automl-lite[onnx,reports]; extra == "all"
Dynamic: license-file
